{"name": "root",
 "children":
 [
 {"name": "System Idle Process", "attributes": {"pid": "0"}, "children": []},
 {"name": "System", "attributes": {"pid": "4"}, "children": [{"name": "Secure System", "children": []}, {"name": "Registry", "children": []}, {"name": "smss.exe", "children": []}, {"name": "Memory Compression", "children": []}]}, {"name": "Secure System", "attributes": {"pid": "72"}, "children": []}, {"name": "LsaIso.exe", "attributes": {"pid": "96"}, "children": []}, {"name": "svchost.exe", "attributes": {"pid": "100"}, "children": []}, {"name": "Registry", "attributes": {"pid": "128"}, "children": []}, {"name": "lsass.exe", "attributes": {"pid": "344"}, "children": []}, {"name": "smss.exe", "attributes": {"pid": "592"}, "children": []}, {"name": "csrss.exe", "attributes": {"pid": "856"}, "children": []}, {"name": "wininit.exe", "attributes": {"pid": "944"}, "children": [{"name": "LsaIso.exe", "children": []}, {"name": "lsass.exe", "children": []}, {"name": "services.exe", "children": [{"name": "svchost.exe", "children": []}, {"name": "svchost.exe", "children": []}, {"name": "svchost.exe", "children": [{"name": "dllhost.exe", "children": []}, {"name": "SettingSyncHost.exe", "children": []}, {"name": "SystemSettings.exe", "children": []}, {"name": "WmiPrvSE.exe", "children": []}, {"name": "smartscreen.exe", "children": []}, {"name": "Calculator.exe", "children": []}, {"name": "browser_broker.exe", "children": []}, {"name": "unsecapp.exe", "children": []}, {"name": "RuntimeBroker.exe", "children": [{"name": "MicrosoftEdgeSH.exe", "children": []}]}, {"name": "YourPhone.exe", "children": []}, {"name": "RuntimeBroker.exe", "children": []}, {"name": "ApplicationFrameHost.exe", "children": []}, {"name": "StartMenuExperienceHost.exe", "children": []}, {"name": "WindowsInternal.ComposableShell.Experiences.TextInput.InputApp.exe", "children": []}, {"name": "RuntimeBroker.exe", "children": []}, {"name": "YourPhoneServer.exe", "children": []}, {"name": "SearchUI.exe", "children": []}, {"name": "RuntimeBroker.exe", "children": []}, {"name": "ShellExperienceHost.exe", "children": []}, {"name": "SkypeApp.exe", "children": []}, {"name": "SkypeBackgroundHost.exe", "children": []}, {"name": "LockApp.exe", "children": []}, {"name": "RuntimeBroker.exe", "children": []}, {"name": "RuntimeBroker.exe", "children": []}, {"name": "igfxext.exe", "children": []}, {"name": "RuntimeBroker.exe", "children": [{"name": "SkypeBridge.exe", "children": []}]}, {"name": "SecurityHealthHost.exe", "children": []}, {"name": "RuntimeBroker.exe", "children": []}, {"name": "CompPkgSrv.exe", "children": []}, {"name": "RuntimeBroker.exe", "children": []}, {"name": "Microsoft.Photos.exe", "children": []}, {"name": "MicrosoftEdge.exe", "children": []}, {"name": "RuntimeBroker.exe", "children": []}, {"name": "MicrosoftEdgeCP.exe", "children": []}, {"name": "WmiPrvSE.exe", "children": []}]}, {"name": "WUDFHost.exe", "children": []}, {"name": "svchost.exe", "children": []}, {"name": "svchost.exe", "children": []}, {"name": "svchost.exe", "children": []}, {"name": "WUDFHost.exe", "children": []}, {"name": "WUDFHost.exe", "children": []}, {"name": "WUDFHost.exe", "children": []}, {"name": "svchost.exe", "children": []}, {"name": "svchost.exe", "children": []}, {"name": "svchost.exe", "children": []}, {"name": "svchost.exe", "children": []}, {"name": "svchost.exe", "children": []}, {"name": "svchost.exe", "children": []}, {"name": "svchost.exe", "children": []}, {"name": "svchost.exe", "children": []}, {"name": "svchost.exe", "children": []}, {"name": "svchost.exe", "children": []}, {"name": "svchost.exe", "children": []}, {"name": "svchost.exe", "children": []}, {"name": "svchost.exe", "children": []}, {"name": "svchost.exe", "children": []}, {"name": "svchost.exe", "children": []}, {"name": "svchost.exe", "children": []}, {"name": "svchost.exe", "children": []}, {"name": "svchost.exe", "children": [{"name": "dasHost.exe", "children": []}]}, {"name": "igfxCUIService.exe", "children": [{"name": "igfxEM.exe", "children": []}]}, {"name": "svchost.exe", "children": []}, {"name": "LITSSvc.exe", "children": []}, {"name": "ibmpmsvc.exe", "children": []}, {"name": "svchost.exe", "children": []}, {"name": "svchost.exe", "children": [{"name": "sihost.exe", "children": [{"name": "PaintStudio.View.exe", "children": []}]}]}, {"name": "svchost.exe", "children": []}, {"name": "svchost.exe", "children": []}, {"name": "svchost.exe", "children": []}, {"name": "svchost.exe", "children": []}, {"name": "svchost.exe", "children": [{"name": "taskhostw.exe", "children": []}, {"name": "PowerMgr.exe", "children": []}, {"name": "RtkAudUService64.exe", "children": []}]}, {"name": "svchost.exe", "children": []}, {"name": "spoolsv.exe", "children": []}, {"name": "svchost.exe", "children": []}, {"name": "svchost.exe", "children": []}, {"name": "svchost.exe", "children": []}, {"name": "svchost.exe", "children": []}, {"name": "svchost.exe", "children": []}, {"name": "svchost.exe", "children": []}, {"name": "svchost.exe", "children": [{"name": "audiodg.exe", "children": []}]}, {"name": "svchost.exe", "children": []}, {"name": "svchost.exe", "children": []}, {"name": "svchost.exe", "children": []}, {"name": "svchost.exe", "children": [{"name": "wlanext.exe", "children": [{"name": "conhost.exe", "children": []}]}]}, {"name": "svchost.exe", "children": []}, {"name": "SgrmBroker.exe", "children": []}, {"name": "svchost.exe", "children": []}, {"name": "svchost.exe", "children": []}, {"name": "svchost.exe", "children": []}, {"name": "svchost.exe", "children": []}, {"name": "svchost.exe", "children": []}, {"name": "svchost.exe", "children": []}, {"name": "svchost.exe", "children": []}, {"name": "svchost.exe", "children": []}, {"name": "IntelCpHDCPSvc.exe", "children": []}, {"name": "svchost.exe", "children": []}, {"name": "DAX3API.exe", "children": [{"name": "DAX3API.exe", "children": []}]}, {"name": "svchost.exe", "children": []}, {"name": "Lenovo.Modern.ImController.exe", "children": [{"name": "Lenovo.Modern.ImController.PluginHost.SettingsApp.exe", "children": []}, {"name": "Lenovo.Modern.ImController.PluginHost.CompanionApp.exe", "children": []}, {"name": "Lenovo.Modern.ImController.PluginHost.Device.exe", "children": []}]}, {"name": "esif_uf.exe", "children": []}, {"name": "svchost.exe", "children": []}, {"name": "ApsInsSvc.exe", "children": []}, {"name": "EvtEng.exe", "children": []}, {"name": "FMService64.exe", "children": []}, {"name": "svchost.exe", "children": []}, {"name": "ThunderboltService.exe", "children": []}, {"name": "svchost.exe", "children": []}, {"name": "svchost.exe", "children": []}, {"name": "LMS.exe", "children": []}, {"name": "pg_ctl.exe", "children": [{"name": "postgres.exe", "children": [{"name": "postgres.exe", "children": []}, {"name": "postgres.exe", "children": []}, {"name": "postgres.exe", "children": []}, {"name": "conhost.exe", "children": []}, {"name": "postgres.exe", "children": []}, {"name": "postgres.exe", "children": []}, {"name": "postgres.exe", "children": []}, {"name": "postgres.exe", "children": []}, {"name": "postgres.exe", "children": []}, {"name": "postgres.exe", "children": []}, {"name": "postgres.exe", "children": []}, {"name": "postgres.exe", "children": []}, {"name": "postgres.exe", "children": []}, {"name": "postgres.exe", "children": []}, {"name": "postgres.exe", "children": []}]}]}, {"name": "svchost.exe", "children": []}, {"name": "WirelessKB850NotificationService.exe", "children": []}, {"name": "Updater.exe", "children": []}, {"name": "SynTPEnhService.exe", "children": [{"name": "SynTPEnh.exe", "children": []}]}, {"name": "RtkAudUService64.exe", "children": [{"name": "RtkAudUService64.exe", "children": []}]}, {"name": "SocketHeciServer.exe", "children": []}, {"name": "MsMpEng.exe", "children": []}, {"name": "ZeroConfigService.exe", "children": []}, {"name": "EasyResume.exe", "children": []}, {"name": "mongod.exe", "children": []}, {"name": "svchost.exe", "children": []}, {"name": "svchost.exe", "children": []}, {"name": "svchost.exe", "children": []}, {"name": "svchost.exe", "children": []}, {"name": "tphkload.exe", "children": [{"name": "shtctky.exe", "children": []}, {"name": "tposd.exe", "children": []}]}, {"name": "vmms.exe", "children": []}, {"name": "LenovoVantageService.exe", "children": []}, {"name": "IntelCpHeciSvc.exe", "children": []}, {"name": "DolbyDAX2API.exe", "children": []}, {"name": "jhi_service.exe", "children": []}, {"name": "vmcompute.exe", "children": []}, {"name": "svchost.exe", "children": []}, {"name": "svchost.exe", "children": []}, {"name": "svchost.exe", "children": []}, {"name": "svchost.exe", "children": []}, {"name": "NisSrv.exe", "children": []}, {"name": "tbtsvc.exe", "children": []}, {"name": "svchost.exe", "children": []}, {"name": "svchost.exe", "children": []}, {"name": "svchost.exe", "children": []}, {"name": "svchost.exe", "children": []}, {"name": "svchost.exe", "children": []}, {"name": "svchost.exe", "children": []}, {"name": "svchost.exe", "children": [{"name": "ctfmon.exe", "children": []}]}, {"name": "svchost.exe", "children": []}, {"name": "svchost.exe", "children": []}, {"name": "svchost.exe", "children": []}, {"name": "svchost.exe", "children": []}, {"name": "svchost.exe", "children": []}, {"name": "svchost.exe", "children": []}, {"name": "svchost.exe", "children": []}, {"name": "SearchIndexer.exe", "children": [{"name": "SearchFilterHost.exe", "children": []}, {"name": "SearchProtocolHost.exe", "children": []}]}, {"name": "svchost.exe", "children": []}, {"name": "svchost.exe", "children": []}, {"name": "aesm_service.exe", "children": []}, {"name": "com.docker.service", "children": []}, {"name": "SecurityHealthService.exe", "children": []}, {"name": "svchost.exe", "children": []}, {"name": "svchost.exe", "children": []}, {"name": "svchost.exe", "children": []}, {"name": "svchost.exe", "children": []}, {"name": "svchost.exe", "children": []}, {"name": "svchost.exe", "children": []}, {"name": "svchost.exe", "children": []}]}, {"name": "fontdrvhost.exe", "children": []}]}, {"name": "csrss.exe", "attributes": {"pid": "952"}, "children": []}, {"name": "services.exe", "attributes": {"pid": "1016"}, "children": [{"name": "svchost.exe", "children": []}, {"name": "svchost.exe", "children": []}, {"name": "svchost.exe", "children": [{"name": "dllhost.exe", "children": []}, {"name": "SettingSyncHost.exe", "children": []}, {"name": "SystemSettings.exe", "children": []}, {"name": "WmiPrvSE.exe", "children": []}, {"name": "smartscreen.exe", "children": []}, {"name": "Calculator.exe", "children": []}, {"name": "browser_broker.exe", "children": []}, {"name": "unsecapp.exe", "children": []}, {"name": "RuntimeBroker.exe", "children": [{"name": "MicrosoftEdgeSH.exe", "children": []}]}, {"name": "YourPhone.exe", "children": []}, {"name": "RuntimeBroker.exe", "children": []}, {"name": "ApplicationFrameHost.exe", "children": []}, {"name": "StartMenuExperienceHost.exe", "children": []}, {"name": "WindowsInternal.ComposableShell.Experiences.TextInput.InputApp.exe", "children": []}, {"name": "RuntimeBroker.exe", "children": []}, {"name": "YourPhoneServer.exe", "children": []}, {"name": "SearchUI.exe", "children": []}, {"name": "RuntimeBroker.exe", "children": []}, {"name": "ShellExperienceHost.exe", "children": []}, {"name": "SkypeApp.exe", "children": []}, {"name": "SkypeBackgroundHost.exe", "children": []}, {"name": "LockApp.exe", "children": []}, {"name": "RuntimeBroker.exe", "children": []}, {"name": "RuntimeBroker.exe", "children": []}, {"name": "igfxext.exe", "children": []}, {"name": "RuntimeBroker.exe", "children": [{"name": "SkypeBridge.exe", "children": []}]}, {"name": "SecurityHealthHost.exe", "children": []}, {"name": "RuntimeBroker.exe", "children": []}, {"name": "CompPkgSrv.exe", "children": []}, {"name": "RuntimeBroker.exe", "children": []}, {"name": "Microsoft.Photos.exe", "children": []}, {"name": "MicrosoftEdge.exe", "children": []}, {"name": "RuntimeBroker.exe", "children": []}, {"name": "MicrosoftEdgeCP.exe", "children": []}, {"name": "WmiPrvSE.exe", "children": []}]}, {"name": "WUDFHost.exe", "children": []}, {"name": "svchost.exe", "children": []}, {"name": "svchost.exe", "children": []}, {"name": "svchost.exe", "children": []}, {"name": "WUDFHost.exe", "children": []}, {"name": "WUDFHost.exe", "children": []}, {"name": "WUDFHost.exe", "children": []}, {"name": "svchost.exe", "children": []}, {"name": "svchost.exe", "children": []}, {"name": "svchost.exe", "children": []}, {"name": "svchost.exe", "children": []}, {"name": "svchost.exe", "children": []}, {"name": "svchost.exe", "children": []}, {"name": "svchost.exe", "children": []}, {"name": "svchost.exe", "children": []}, {"name": "svchost.exe", "children": []}, {"name": "svchost.exe", "children": []}, {"name": "svchost.exe", "children": []}, {"name": "svchost.exe", "children": []}, {"name": "svchost.exe", "children": []}, {"name": "svchost.exe", "children": []}, {"name": "svchost.exe", "children": []}, {"name": "svchost.exe", "children": []}, {"name": "svchost.exe", "children": []}, {"name": "svchost.exe", "children": [{"name": "dasHost.exe", "children": []}]}, {"name": "igfxCUIService.exe", "children": [{"name": "igfxEM.exe", "children": []}]}, {"name": "svchost.exe", "children": []}, {"name": "LITSSvc.exe", "children": []}, {"name": "ibmpmsvc.exe", "children": []}, {"name": "svchost.exe", "children": []}, {"name": "svchost.exe", "children": [{"name": "sihost.exe", "children": [{"name": "PaintStudio.View.exe", "children": []}]}]}, {"name": "svchost.exe", "children": []}, {"name": "svchost.exe", "children": []}, {"name": "svchost.exe", "children": []}, {"name": "svchost.exe", "children": []}, {"name": "svchost.exe", "children": [{"name": "taskhostw.exe", "children": []}, {"name": "PowerMgr.exe", "children": []}, {"name": "RtkAudUService64.exe", "children": []}]}, {"name": "svchost.exe", "children": []}, {"name": "spoolsv.exe", "children": []}, {"name": "svchost.exe", "children": []}, {"name": "svchost.exe", "children": []}, {"name": "svchost.exe", "children": []}, {"name": "svchost.exe", "children": []}, {"name": "svchost.exe", "children": []}, {"name": "svchost.exe", "children": []}, {"name": "svchost.exe", "children": [{"name": "audiodg.exe", "children": []}]}, {"name": "svchost.exe", "children": []}, {"name": "svchost.exe", "children": []}, {"name": "svchost.exe", "children": []}, {"name": "svchost.exe", "children": [{"name": "wlanext.exe", "children": [{"name": "conhost.exe", "children": []}]}]}, {"name": "svchost.exe", "children": []}, {"name": "SgrmBroker.exe", "children": []}, {"name": "svchost.exe", "children": []}, {"name": "svchost.exe", "children": []}, {"name": "svchost.exe", "children": []}, {"name": "svchost.exe", "children": []}, {"name": "svchost.exe", "children": []}, {"name": "svchost.exe", "children": []}, {"name": "svchost.exe", "children": []}, {"name": "svchost.exe", "children": []}, {"name": "IntelCpHDCPSvc.exe", "children": []}, {"name": "svchost.exe", "children": []}, {"name": "DAX3API.exe", "children": [{"name": "DAX3API.exe", "children": []}]}, {"name": "svchost.exe", "children": []}, {"name": "Lenovo.Modern.ImController.exe", "children": [{"name": "Lenovo.Modern.ImController.PluginHost.SettingsApp.exe", "children": []}, {"name": "Lenovo.Modern.ImController.PluginHost.CompanionApp.exe", "children": []}, {"name": "Lenovo.Modern.ImController.PluginHost.Device.exe", "children": []}]}, {"name": "esif_uf.exe", "children": []}, {"name": "svchost.exe", "children": []}, {"name": "ApsInsSvc.exe", "children": []}, {"name": "EvtEng.exe", "children": []}, {"name": "FMService64.exe", "children": []}, {"name": "svchost.exe", "children": []}, {"name": "ThunderboltService.exe", "children": []}, {"name": "svchost.exe", "children": []}, {"name": "svchost.exe", "children": []}, {"name": "LMS.exe", "children": []}, {"name": "pg_ctl.exe", "children": [{"name": "postgres.exe", "children": [{"name": "postgres.exe", "children": []}, {"name": "postgres.exe", "children": []}, {"name": "postgres.exe", "children": []}, {"name": "conhost.exe", "children": []}, {"name": "postgres.exe", "children": []}, {"name": "postgres.exe", "children": []}, {"name": "postgres.exe", "children": []}, {"name": "postgres.exe", "children": []}, {"name": "postgres.exe", "children": []}, {"name": "postgres.exe", "children": []}, {"name": "postgres.exe", "children": []}, {"name": "postgres.exe", "children": []}, {"name": "postgres.exe", "children": []}, {"name": "postgres.exe", "children": []}, {"name": "postgres.exe", "children": []}]}]}, {"name": "svchost.exe", "children": []}, {"name": "WirelessKB850NotificationService.exe", "children": []}, {"name": "Updater.exe", "children": []}, {"name": "SynTPEnhService.exe", "children": [{"name": "SynTPEnh.exe", "children": []}]}, {"name": "RtkAudUService64.exe", "children": [{"name": "RtkAudUService64.exe", "children": []}]}, {"name": "SocketHeciServer.exe", "children": []}, {"name": "MsMpEng.exe", "children": []}, {"name": "ZeroConfigService.exe", "children": []}, {"name": "EasyResume.exe", "children": []}, {"name": "mongod.exe", "children": []}, {"name": "svchost.exe", "children": []}, {"name": "svchost.exe", "children": []}, {"name": "svchost.exe", "children": []}, {"name": "svchost.exe", "children": []}, {"name": "tphkload.exe", "children": [{"name": "shtctky.exe", "children": []}, {"name": "tposd.exe", "children": []}]}, {"name": "vmms.exe", "children": []}, {"name": "LenovoVantageService.exe", "children": []}, {"name": "IntelCpHeciSvc.exe", "children": []}, {"name": "DolbyDAX2API.exe", "children": []}, {"name": "jhi_service.exe", "children": []}, {"name": "vmcompute.exe", "children": []}, {"name": "svchost.exe", "children": []}, {"name": "svchost.exe", "children": []}, {"name": "svchost.exe", "children": []}, {"name": "svchost.exe", "children": []}, {"name": "NisSrv.exe", "children": []}, {"name": "tbtsvc.exe", "children": []}, {"name": "svchost.exe", "children": []}, {"name": "svchost.exe", "children": []}, {"name": "svchost.exe", "children": []}, {"name": "svchost.exe", "children": []}, {"name": "svchost.exe", "children": []}, {"name": "svchost.exe", "children": []}, {"name": "svchost.exe", "children": [{"name": "ctfmon.exe", "children": []}]}, {"name": "svchost.exe", "children": []}, {"name": "svchost.exe", "children": []}, {"name": "svchost.exe", "children": []}, {"name": "svchost.exe", "children": []}, {"name": "svchost.exe", "children": []}, {"name": "svchost.exe", "children": []}, {"name": "svchost.exe", "children": []}, {"name": "SearchIndexer.exe", "children": [{"name": "SearchFilterHost.exe", "children": []}, {"name": "SearchProtocolHost.exe", "children": []}]}, {"name": "svchost.exe", "children": []}, {"name": "svchost.exe", "children": []}, {"name": "aesm_service.exe", "children": []}, {"name": "com.docker.service", "children": []}, {"name": "SecurityHealthService.exe", "children": []}, {"name": "svchost.exe", "children": []}, {"name": "svchost.exe", "children": []}, {"name": "svchost.exe", "children": []}, {"name": "svchost.exe", "children": []}, {"name": "svchost.exe", "children": []}, {"name": "svchost.exe", "children": []}, {"name": "svchost.exe", "children": []}]}, {"name": "svchost.exe", "attributes": {"pid": "1048"}, "children": []}, {"name": "svchost.exe", "attributes": {"pid": "1072"}, "children": [{"name": "dllhost.exe", "children": []}, {"name": "SettingSyncHost.exe", "children": []}, {"name": "SystemSettings.exe", "children": []}, {"name": "WmiPrvSE.exe", "children": []}, {"name": "smartscreen.exe", "children": []}, {"name": "Calculator.exe", "children": []}, {"name": "browser_broker.exe", "children": []}, {"name": "unsecapp.exe", "children": []}, {"name": "RuntimeBroker.exe", "children": [{"name": "MicrosoftEdgeSH.exe", "children": []}]}, {"name": "YourPhone.exe", "children": []}, {"name": "RuntimeBroker.exe", "children": []}, {"name": "ApplicationFrameHost.exe", "children": []}, {"name": "StartMenuExperienceHost.exe", "children": []}, {"name": "WindowsInternal.ComposableShell.Experiences.TextInput.InputApp.exe", "children": []}, {"name": "RuntimeBroker.exe", "children": []}, {"name": "YourPhoneServer.exe", "children": []}, {"name": "SearchUI.exe", "children": []}, {"name": "RuntimeBroker.exe", "children": []}, {"name": "ShellExperienceHost.exe", "children": []}, {"name": "SkypeApp.exe", "children": []}, {"name": "SkypeBackgroundHost.exe", "children": []}, {"name": "LockApp.exe", "children": []}, {"name": "RuntimeBroker.exe", "children": []}, {"name": "RuntimeBroker.exe", "children": []}, {"name": "igfxext.exe", "children": []}, {"name": "RuntimeBroker.exe", "children": [{"name": "SkypeBridge.exe", "children": []}]}, {"name": "SecurityHealthHost.exe", "children": []}, {"name": "RuntimeBroker.exe", "children": []}, {"name": "CompPkgSrv.exe", "children": []}, {"name": "RuntimeBroker.exe", "children": []}, {"name": "Microsoft.Photos.exe", "children": []}, {"name": "MicrosoftEdge.exe", "children": []}, {"name": "RuntimeBroker.exe", "children": []}, {"name": "MicrosoftEdgeCP.exe", "children": []}, {"name": "WmiPrvSE.exe", "children": []}]}, {"name": "fontdrvhost.exe", "attributes": {"pid": "1096"}, "children": []}, {"name": "WUDFHost.exe", "attributes": {"pid": "1104"}, "children": []}, {"name": "svchost.exe", "attributes": {"pid": "1196"}, "children": []}, {"name": "svchost.exe", "attributes": {"pid": "1240"}, "children": []}, {"name": "svchost.exe", "attributes": {"pid": "1244"}, "children": []}, {"name": "SearchFilterHost.exe", "attributes": {"pid": "1284"}, "children": []}, {"name": "python.exe", "attributes": {"pid": "1288"}, "children": [{"name": "conhost.exe", "children": []}]}, {"name": "WUDFHost.exe", "attributes": {"pid": "1308"}, "children": []}, {"name": "WUDFHost.exe", "attributes": {"pid": "1348"}, "children": []}, {"name": "winlogon.exe", "attributes": {"pid": "1416"}, "children": [{"name": "fontdrvhost.exe", "children": []}, {"name": "dwm.exe", "children": []}]}, {"name": "python.exe", "attributes": {"pid": "1424"}, "children": []}, {"name": "WUDFHost.exe", "attributes": {"pid": "1488"}, "children": []}, {"name": "bash.exe", "attributes": {"pid": "1536"}, "children": [{"name": "python.exe", "children": []}]}, {"name": "fontdrvhost.exe", "attributes": {"pid": "1548"}, "children": []}, {"name": "dwm.exe", "attributes": {"pid": "1624"}, "children": []}, {"name": "chrome.exe", "attributes": {"pid": "1700"}, "children": []}, {"name": "svchost.exe", "attributes": {"pid": "1704"}, "children": []}, {"name": "svchost.exe", "attributes": {"pid": "1716"}, "children": []}, {"name": "svchost.exe", "attributes": {"pid": "1736"}, "children": []}, {"name": "svchost.exe", "attributes": {"pid": "1772"}, "children": []}, {"name": "svchost.exe", "attributes": {"pid": "1836"}, "children": []}, {"name": "Code.exe", "attributes": {"pid": "1852"}, "children": []}, {"name": "svchost.exe", "attributes": {"pid": "1940"}, "children": []}, {"name": "client.exe", "attributes": {"pid": "1996"}, "children": [{"name": "client.exe", "children": []}]}, {"name": "svchost.exe", "attributes": {"pid": "2040"}, "children": []}, {"name": "svchost.exe", "attributes": {"pid": "2072"}, "children": []}, {"name": "svchost.exe", "attributes": {"pid": "2088"}, "children": []}, {"name": "svchost.exe", "attributes": {"pid": "2112"}, "children": []}, {"name": "svchost.exe", "attributes": {"pid": "2128"}, "children": []}, {"name": "svchost.exe", "attributes": {"pid": "2200"}, "children": []}, {"name": "svchost.exe", "attributes": {"pid": "2248"}, "children": []}, {"name": "svchost.exe", "attributes": {"pid": "2272"}, "children": []}, {"name": "svchost.exe", "attributes": {"pid": "2308"}, "children": []}, {"name": "svchost.exe", "attributes": {"pid": "2376"}, "children": []}, {"name": "svchost.exe", "attributes": {"pid": "2384"}, "children": []}, {"name": "svchost.exe", "attributes": {"pid": "2392"}, "children": [{"name": "dasHost.exe", "children": []}]}, {"name": "igfxCUIService.exe", "attributes": {"pid": "2400"}, "children": [{"name": "igfxEM.exe", "children": []}]}, {"name": "svchost.exe", "attributes": {"pid": "2416"}, "children": []}, {"name": "LITSSvc.exe", "attributes": {"pid": "2516"}, "children": []}, {"name": "ibmpmsvc.exe", "attributes": {"pid": "2524"}, "children": []}, {"name": "Lenovo.Modern.ImController.PluginHost.SettingsApp.exe", "attributes": {"pid": "2572"}, "children": []}, {"name": "svchost.exe", "attributes": {"pid": "2592"}, "children": []}, {"name": "svchost.exe", "attributes": {"pid": "2692"}, "children": [{"name": "sihost.exe", "children": [{"name": "PaintStudio.View.exe", "children": []}]}]}, {"name": "slack.exe", "attributes": {"pid": "2700"}, "children": []}, {"name": "chrome.exe", "attributes": {"pid": "2704"}, "children": []}, {"name": "dasHost.exe", "attributes": {"pid": "2708"}, "children": []}, {"name": "svchost.exe", "attributes": {"pid": "2816"}, "children": []}, {"name": "slack.exe", "attributes": {"pid": "2848"}, "children": []}, {"name": "svchost.exe", "attributes": {"pid": "2868"}, "children": []}, {"name": "svchost.exe", "attributes": {"pid": "2880"}, "children": []}, {"name": "svchost.exe", "attributes": {"pid": "2980"}, "children": []}, {"name": "svchost.exe", "attributes": {"pid": "3012"}, "children": [{"name": "taskhostw.exe", "children": []}, {"name": "PowerMgr.exe", "children": []}, {"name": "RtkAudUService64.exe", "children": []}]}, {"name": "svchost.exe", "attributes": {"pid": "3068"}, "children": []}, {"name": "spoolsv.exe", "attributes": {"pid": "3084"}, "children": []}, {"name": "Memory Compression", "attributes": {"pid": "3104"}, "children": []}, {"name": "svchost.exe", "attributes": {"pid": "3120"}, "children": []}, {"name": "svchost.exe", "attributes": {"pid": "3188"}, "children": []}, {"name": "taskhostw.exe", "attributes": {"pid": "3264"}, "children": []}, {"name": "svchost.exe", "attributes": {"pid": "3368"}, "children": []}, {"name": "svchost.exe", "attributes": {"pid": "3380"}, "children": []}, {"name": "postgres.exe", "attributes": {"pid": "3452"}, "children": []}, {"name": "svchost.exe", "attributes": {"pid": "3524"}, "children": []}, {"name": "svchost.exe", "attributes": {"pid": "3540"}, "children": []}, {"name": "svchost.exe", "attributes": {"pid": "3620"}, "children": [{"name": "audiodg.exe", "children": []}]}, {"name": "svchost.exe", "attributes": {"pid": "3628"}, "children": []}, {"name": "svchost.exe", "attributes": {"pid": "3700"}, "children": []}, {"name": "svchost.exe", "attributes": {"pid": "3708"}, "children": []}, {"name": "cmd.exe", "attributes": {"pid": "3724"}, "children": []}, {"name": "svchost.exe", "attributes": {"pid": "3924"}, "children": [{"name": "wlanext.exe", "children": [{"name": "conhost.exe", "children": []}]}]}, {"name": "svchost.exe", "attributes": {"pid": "4032"}, "children": []}, {"name": "SgrmBroker.exe", "attributes": {"pid": "4104"}, "children": []}, {"name": "wlanext.exe", "attributes": {"pid": "4124"}, "children": [{"name": "conhost.exe", "children": []}]}, {"name": "conhost.exe", "attributes": {"pid": "4136"}, "children": []}, {"name": "svchost.exe", "attributes": {"pid": "4168"}, "children": []}, {"name": "notepad++.exe", "attributes": {"pid": "4196"}, "children": []}, {"name": "svchost.exe", "attributes": {"pid": "4228"}, "children": []}, {"name": "svchost.exe", "attributes": {"pid": "4280"}, "children": []}, {"name": "svchost.exe", "attributes": {"pid": "4472"}, "children": []}, {"name": "svchost.exe", "attributes": {"pid": "4480"}, "children": []}, {"name": "MicrosoftEdgeSH.exe", "attributes": {"pid": "4500"}, "children": []}, {"name": "Code.exe", "attributes": {"pid": "4548"}, "children": [{"name": "Code.exe", "children": []}, {"name": "Code.exe", "children": []}, {"name": "Code.exe", "children": []}, {"name": "Code.exe", "children": [{"name": "conhost.exe", "children": []}, {"name": "bash.exe", "children": [{"name": "bash.exe", "children": []}]}, {"name": "bash.exe", "children": [{"name": "bash.exe", "children": []}]}, {"name": "Code.exe", "children": [{"name": "Code.exe", "children": []}, {"name": "Code.exe", "children": []}, {"name": "Code.exe", "children": []}, {"name": "Code.exe", "children": [{"name": "Code.exe", "children": []}]}, {"name": "Code.exe", "children": []}]}, {"name": "CodeHelper.exe", "children": [{"name": "conhost.exe", "children": []}]}, {"name": "conhost.exe", "children": []}]}, {"name": "Code.exe", "children": []}]}, {"name": "shtctky.exe", "attributes": {"pid": "4592"}, "children": []}, {"name": "dllhost.exe", "attributes": {"pid": "4596"}, "children": []}, {"name": "conhost.exe", "attributes": {"pid": "4600"}, "children": []}, {"name": "RtkAudUService64.exe", "attributes": {"pid": "4680"}, "children": []}, {"name": "svchost.exe", "attributes": {"pid": "4696"}, "children": []}, {"name": "svchost.exe", "attributes": {"pid": "4716"}, "children": []}, {"name": "svchost.exe", "attributes": {"pid": "4724"}, "children": []}, {"name": "chrome.exe", "attributes": {"pid": "4736"}, "children": []}, {"name": "IntelCpHDCPSvc.exe", "attributes": {"pid": "4740"}, "children": []}, {"name": "svchost.exe", "attributes": {"pid": "4748"}, "children": []}, {"name": "DAX3API.exe", "attributes": {"pid": "4756"}, "children": [{"name": "DAX3API.exe", "children": []}]}, {"name": "svchost.exe", "attributes": {"pid": "4764"}, "children": []}, {"name": "Lenovo.Modern.ImController.exe", "attributes": {"pid": "4772"}, "children": [{"name": "Lenovo.Modern.ImController.PluginHost.SettingsApp.exe", "children": []}, {"name": "Lenovo.Modern.ImController.PluginHost.CompanionApp.exe", "children": []}, {"name": "Lenovo.Modern.ImController.PluginHost.Device.exe", "children": []}]}, {"name": "esif_uf.exe", "attributes": {"pid": "4788"}, "children": []}, {"name": "svchost.exe", "attributes": {"pid": "4796"}, "children": []}, {"name": "ApsInsSvc.exe", "attributes": {"pid": "4804"}, "children": []}, {"name": "EvtEng.exe", "attributes": {"pid": "4812"}, "children": []}, {"name": "FMService64.exe", "attributes": {"pid": "4820"}, "children": []}, {"name": "svchost.exe", "attributes": {"pid": "4828"}, "children": []}, {"name": "ThunderboltService.exe", "attributes": {"pid": "4844"}, "children": []}, {"name": "svchost.exe", "attributes": {"pid": "4860"}, "children": []}, {"name": "svchost.exe", "attributes": {"pid": "4872"}, "children": []}, {"name": "LMS.exe", "attributes": {"pid": "4880"}, "children": []}, {"name": "pg_ctl.exe", "attributes": {"pid": "4888"}, "children": [{"name": "postgres.exe", "children": [{"name": "postgres.exe", "children": []}, {"name": "postgres.exe", "children": []}, {"name": "postgres.exe", "children": []}, {"name": "conhost.exe", "children": []}, {"name": "postgres.exe", "children": []}, {"name": "postgres.exe", "children": []}, {"name": "postgres.exe", "children": []}, {"name": "postgres.exe", "children": []}, {"name": "postgres.exe", "children": []}, {"name": "postgres.exe", "children": []}, {"name": "postgres.exe", "children": []}, {"name": "postgres.exe", "children": []}, {"name": "postgres.exe", "children": []}, {"name": "postgres.exe", "children": []}, {"name": "postgres.exe", "children": []}]}]}, {"name": "svchost.exe", "attributes": {"pid": "4896"}, "children": []}, {"name": "WirelessKB850NotificationService.exe", "attributes": {"pid": "4904"}, "children": []}, {"name": "Updater.exe", "attributes": {"pid": "4912"}, "children": []}, {"name": "SynTPEnhService.exe", "attributes": {"pid": "4920"}, "children": [{"name": "SynTPEnh.exe", "children": []}]}, {"name": "RtkAudUService64.exe", "attributes": {"pid": "4928"}, "children": [{"name": "RtkAudUService64.exe", "children": []}]}, {"name": "SocketHeciServer.exe", "attributes": {"pid": "4972"}, "children": []}, {"name": "MsMpEng.exe", "attributes": {"pid": "4984"}, "children": []}, {"name": "ZeroConfigService.exe", "attributes": {"pid": "5024"}, "children": []}, {"name": "EasyResume.exe", "attributes": {"pid": "5040"}, "children": []}, {"name": "SettingSyncHost.exe", "attributes": {"pid": "5048"}, "children": []}, {"name": "mongod.exe", "attributes": {"pid": "5060"}, "children": []}, {"name": "svchost.exe", "attributes": {"pid": "5128"}, "children": []}, {"name": "svchost.exe", "attributes": {"pid": "5536"}, "children": []}, {"name": "SystemSettings.exe", "attributes": {"pid": "5568"}, "children": []}, {"name": "svchost.exe", "attributes": {"pid": "5744"}, "children": []}, {"name": "svchost.exe", "attributes": {"pid": "5820"}, "children": []}, {"name": "tphkload.exe", "attributes": {"pid": "5832"}, "children": [{"name": "shtctky.exe", "children": []}, {"name": "tposd.exe", "children": []}]}, {"name": "postgres.exe", "attributes": {"pid": "5864"}, "children": []}, {"name": "vmms.exe", "attributes": {"pid": "5884"}, "children": []}, {"name": "LenovoVantageService.exe", "attributes": {"pid": "5908"}, "children": []}, {"name": "postgres.exe", "attributes": {"pid": "5928"}, "children": []}, {"name": "IntelCpHeciSvc.exe", "attributes": {"pid": "5992"}, "children": []}, {"name": "WmiPrvSE.exe", "attributes": {"pid": "6204"}, "children": []}, {"name": "DolbyDAX2API.exe", "attributes": {"pid": "6236"}, "children": []}, {"name": "jhi_service.exe", "attributes": {"pid": "6268"}, "children": []}, {"name": "smartscreen.exe", "attributes": {"pid": "6332"}, "children": []}, {"name": "Code.exe", "attributes": {"pid": "6428"}, "children": []}, {"name": "postgres.exe", "attributes": {"pid": "6432"}, "children": [{"name": "postgres.exe", "children": []}, {"name": "postgres.exe", "children": []}, {"name": "postgres.exe", "children": []}, {"name": "conhost.exe", "children": []}, {"name": "postgres.exe", "children": []}, {"name": "postgres.exe", "children": []}, {"name": "postgres.exe", "children": []}, {"name": "postgres.exe", "children": []}, {"name": "postgres.exe", "children": []}, {"name": "postgres.exe", "children": []}, {"name": "postgres.exe", "children": []}, {"name": "postgres.exe", "children": []}, {"name": "postgres.exe", "children": []}, {"name": "postgres.exe", "children": []}, {"name": "postgres.exe", "children": []}]}, {"name": "conhost.exe", "attributes": {"pid": "6452"}, "children": []}, {"name": "conhost.exe", "attributes": {"pid": "6564"}, "children": []}, {"name": "postgres.exe", "attributes": {"pid": "6692"}, "children": []}, {"name": "Calculator.exe", "attributes": {"pid": "6808"}, "children": []}, {"name": "chrome.exe", "attributes": {"pid": "6816"}, "children": []}, {"name": "pgAdmin4.exe", "attributes": {"pid": "6820"}, "children": []}, {"name": "postgres.exe", "attributes": {"pid": "6868"}, "children": []}, {"name": "browser_broker.exe", "attributes": {"pid": "6932"}, "children": []}, {"name": "unsecapp.exe", "attributes": {"pid": "6996"}, "children": []}, {"name": "sh.exe", "attributes": {"pid": "7132"}, "children": [{"name": "node.exe", "children": [{"name": "cmd.exe", "children": [{"name": "node.exe", "children": [{"name": "node.exe", "children": []}]}]}]}]}, {"name": "postgres.exe", "attributes": {"pid": "7148"}, "children": []}, {"name": "postgres.exe", "attributes": {"pid": "7172"}, "children": []}, {"name": "postgres.exe", "attributes": {"pid": "7180"}, "children": []}, {"name": "postgres.exe", "attributes": {"pid": "7192"}, "children": []}, {"name": "RuntimeBroker.exe", "attributes": {"pid": "7244"}, "children": [{"name": "MicrosoftEdgeSH.exe", "children": []}]}, {"name": "tposd.exe", "attributes": {"pid": "7304"}, "children": []}, {"name": "vmcompute.exe", "attributes": {"pid": "7452"}, "children": []}, {"name": "DAX3API.exe", "attributes": {"pid": "7628"}, "children": []}, {"name": "svchost.exe", "attributes": {"pid": "7716"}, "children": []}, {"name": "svchost.exe", "attributes": {"pid": "7784"}, "children": []}, {"name": "UMCAudioCplApp.exe", "attributes": {"pid": "7796"}, "children": []}, {"name": "conhost.exe", "attributes": {"pid": "7836"}, "children": []}, {"name": "SynTPEnh.exe", "attributes": {"pid": "7900"}, "children": []}, {"name": "YourPhone.exe", "attributes": {"pid": "7920"}, "children": []}, {"name": "pycharm64.exe", "attributes": {"pid": "7940"}, "children": [{"name": "python.exe", "children": [{"name": "conhost.exe", "children": []}]}, {"name": "fsnotifier64.exe", "children": [{"name": "conhost.exe", "children": []}]}, {"name": "winpty-agent.exe", "children": [{"name": "cmd.exe", "children": []}, {"name": "conhost.exe", "children": []}]}, {"name": "winpty-agent.exe", "children": [{"name": "cmd.exe", "children": []}, {"name": "conhost.exe", "children": []}]}, {"name": "runnerw64.exe", "children": [{"name": "conhost.exe", "children": []}, {"name": "python.exe", "children": [{"name": "python.exe", "children": []}]}]}]}, {"name": "svchost.exe", "attributes": {"pid": "7944"}, "children": []}, {"name": "bash.exe", "attributes": {"pid": "8056"}, "children": []}, {"name": "svchost.exe", "attributes": {"pid": "8172"}, "children": []}, {"name": "sihost.exe", "attributes": {"pid": "8240"}, "children": [{"name": "PaintStudio.View.exe", "children": []}]}, {"name": "NisSrv.exe", "attributes": {"pid": "8376"}, "children": []}, {"name": "fsnotifier64.exe", "attributes": {"pid": "8396"}, "children": [{"name": "conhost.exe", "children": []}]}, {"name": "tbtsvc.exe", "attributes": {"pid": "8512"}, "children": []}, {"name": "svchost.exe", "attributes": {"pid": "8580"}, "children": []}, {"name": "svchost.exe", "attributes": {"pid": "8596"}, "children": []}, {"name": "svchost.exe", "attributes": {"pid": "8624"}, "children": []}, {"name": "conhost.exe", "attributes": {"pid": "8652"}, "children": []}, {"name": "RuntimeBroker.exe", "attributes": {"pid": "8832"}, "children": []}, {"name": "svchost.exe", "attributes": {"pid": "8856"}, "children": []}, {"name": "svchost.exe", "attributes": {"pid": "8900"}, "children": []}, {"name": "postgres.exe", "attributes": {"pid": "8960"}, "children": []}, {"name": "ApplicationFrameHost.exe", "attributes": {"pid": "8996"}, "children": []}, {"name": "bash.exe", "attributes": {"pid": "9056"}, "children": [{"name": "bash.exe", "children": []}]}, {"name": "explorer.exe", "attributes": {"pid": "9124"}, "children": [{"name": "client.exe", "children": [{"name": "client.exe", "children": []}]}, {"name": "notepad++.exe", "children": []}, {"name": "Code.exe", "children": [{"name": "Code.exe", "children": []}, {"name": "Code.exe", "children": []}, {"name": "Code.exe", "children": []}, {"name": "Code.exe", "children": [{"name": "conhost.exe", "children": []}, {"name": "bash.exe", "children": [{"name": "bash.exe", "children": []}]}, {"name": "bash.exe", "children": [{"name": "bash.exe", "children": []}]}, {"name": "Code.exe", "children": [{"name": "Code.exe", "children": []}, {"name": "Code.exe", "children": []}, {"name": "Code.exe", "children": []}, {"name": "Code.exe", "children": [{"name": "Code.exe", "children": []}]}, {"name": "Code.exe", "children": []}]}, {"name": "CodeHelper.exe", "children": [{"name": "conhost.exe", "children": []}]}, {"name": "conhost.exe", "children": []}]}, {"name": "Code.exe", "children": []}]}, {"name": "pgAdmin4.exe", "children": []}, {"name": "UMCAudioCplApp.exe", "children": []}, {"name": "pycharm64.exe", "children": [{"name": "python.exe", "children": [{"name": "conhost.exe", "children": []}]}, {"name": "fsnotifier64.exe", "children": [{"name": "conhost.exe", "children": []}]}, {"name": "winpty-agent.exe", "children": [{"name": "cmd.exe", "children": []}, {"name": "conhost.exe", "children": []}]}, {"name": "winpty-agent.exe", "children": [{"name": "cmd.exe", "children": []}, {"name": "conhost.exe", "children": []}]}, {"name": "runnerw64.exe", "children": [{"name": "conhost.exe", "children": []}, {"name": "python.exe", "children": [{"name": "python.exe", "children": []}]}]}]}, {"name": "SecurityHealthSystray.exe", "children": []}, {"name": "Greenshot.exe", "children": []}, {"name": "OneDrive.exe", "children": []}, {"name": "git-bash.exe", "children": [{"name": "mintty.exe", "children": []}]}, {"name": "client.exe", "children": [{"name": "client.exe", "children": []}]}]}, {"name": "svchost.exe", "attributes": {"pid": "9188"}, "children": []}, {"name": "postgres.exe", "attributes": {"pid": "9200"}, "children": []}, {"name": "igfxEM.exe", "attributes": {"pid": "9212"}, "children": []}, {"name": "mintty.exe", "attributes": {"pid": "9320"}, "children": []}, {"name": "svchost.exe", "attributes": {"pid": "9372"}, "children": [{"name": "ctfmon.exe", "children": []}]}, {"name": "Code.exe", "attributes": {"pid": "9544"}, "children": []}, {"name": "GoogleCrashHandler.exe", "attributes": {"pid": "9592"}, "children": []}, {"name": "conhost.exe", "attributes": {"pid": "9616"}, "children": []}, {"name": "GoogleCrashHandler64.exe", "attributes": {"pid": "9636"}, "children": []}, {"name": "ctfmon.exe", "attributes": {"pid": "9660"}, "children": []}, {"name": "chrome.exe", "attributes": {"pid": "9668"}, "children": []}, {"name": "svchost.exe", "attributes": {"pid": "9676"}, "children": []}, {"name": "conhost.exe", "attributes": {"pid": "9712"}, "children": []}, {"name": "chrome.exe", "attributes": {"pid": "9768"}, "children": []}, {"name": "Postman.exe", "attributes": {"pid": "9852"}, "children": []}, {"name": "StartMenuExperienceHost.exe", "attributes": {"pid": "9860"}, "children": []}, {"name": "svchost.exe", "attributes": {"pid": "9896"}, "children": []}, {"name": "svchost.exe", "attributes": {"pid": "9916"}, "children": []}, {"name": "python.exe", "attributes": {"pid": "10076"}, "children": []}, {"name": "chrome.exe", "attributes": {"pid": "10132"}, "children": []}, {"name": "svchost.exe", "attributes": {"pid": "10208"}, "children": []}, {"name": "cmd.exe", "attributes": {"pid": "10432"}, "children": []}, {"name": "svchost.exe", "attributes": {"pid": "10544"}, "children": []}, {"name": "WindowsInternal.ComposableShell.Experiences.TextInput.InputApp.exe", "attributes": {"pid": "10556"}, "children": []}, {"name": "svchost.exe", "attributes": {"pid": "10656"}, "children": []}, {"name": "RuntimeBroker.exe", "attributes": {"pid": "10676"}, "children": []}, {"name": "Postman.exe", "attributes": {"pid": "10688"}, "children": []}, {"name": "chrome.exe", "attributes": {"pid": "10784"}, "children": []}, {"name": "YourPhoneServer.exe", "attributes": {"pid": "10916"}, "children": []}, {"name": "Lenovo.Modern.ImController.PluginHost.CompanionApp.exe", "attributes": {"pid": "10956"}, "children": []}, {"name": "svchost.exe", "attributes": {"pid": "10968"}, "children": []}, {"name": "SynTPHelper.exe", "attributes": {"pid": "11144"}, "children": []}, {"name": "winpty-agent.exe", "attributes": {"pid": "11176"}, "children": [{"name": "cmd.exe", "children": []}, {"name": "conhost.exe", "children": []}]}, {"name": "conhost.exe", "attributes": {"pid": "11204"}, "children": []}, {"name": "SearchIndexer.exe", "attributes": {"pid": "11252"}, "children": [{"name": "SearchFilterHost.exe", "children": []}, {"name": "SearchProtocolHost.exe", "children": []}]}, {"name": "SearchUI.exe", "attributes": {"pid": "11340"}, "children": []}, {"name": "postgres.exe", "attributes": {"pid": "11364"}, "children": []}, {"name": "slack.exe", "attributes": {"pid": "11424"}, "children": [{"name": "slack.exe", "children": []}, {"name": "slack.exe", "children": []}, {"name": "slack.exe", "children": []}, {"name": "slack.exe", "children": []}]}, {"name": "RuntimeBroker.exe", "attributes": {"pid": "11536"}, "children": []}, {"name": "conhost.exe", "attributes": {"pid": "11728"}, "children": []}, {"name": "ShellExperienceHost.exe", "attributes": {"pid": "11744"}, "children": []}, {"name": "PowerMgr.exe", "attributes": {"pid": "11816"}, "children": []}, {"name": "svchost.exe", "attributes": {"pid": "11832"}, "children": []}, {"name": "bash.exe", "attributes": {"pid": "12020"}, "children": [{"name": "bash.exe", "children": [{"name": "python.exe", "children": []}]}]}, {"name": "postgres.exe", "attributes": {"pid": "12104"}, "children": []}, {"name": "SkypeApp.exe", "attributes": {"pid": "12140"}, "children": []}, {"name": "SkypeBackgroundHost.exe", "attributes": {"pid": "12168"}, "children": []}, {"name": "LockApp.exe", "attributes": {"pid": "12256"}, "children": []}, {"name": "Code.exe", "attributes": {"pid": "12280"}, "children": []}, {"name": "RuntimeBroker.exe", "attributes": {"pid": "12360"}, "children": []}, {"name": "svchost.exe", "attributes": {"pid": "12404"}, "children": []}, {"name": "node.exe", "attributes": {"pid": "12444"}, "children": [{"name": "cmd.exe", "children": [{"name": "node.exe", "children": [{"name": "node.exe", "children": []}]}]}]}, {"name": "RuntimeBroker.exe", "attributes": {"pid": "12496"}, "children": []}, {"name": "aesm_service.exe", "attributes": {"pid": "12908"}, "children": []}, {"name": "SkypeBridge.exe", "attributes": {"pid": "12968"}, "children": []}, {"name": "igfxext.exe", "attributes": {"pid": "13112"}, "children": []}, {"name": "RuntimeBroker.exe", "attributes": {"pid": "13200"}, "children": [{"name": "SkypeBridge.exe", "children": []}]}, {"name": "chrome.exe", "attributes": {"pid": "13288"}, "children": []}, {"name": "Code.exe", "attributes": {"pid": "13356"}, "children": []}, {"name": "slack.exe", "attributes": {"pid": "13372"}, "children": []}, {"name": "SearchProtocolHost.exe", "attributes": {"pid": "13556"}, "children": []}, {"name": "RtkAudUService64.exe", "attributes": {"pid": "13576"}, "children": []}, {"name": "SecurityHealthHost.exe", "attributes": {"pid": "13612"}, "children": []}, {"name": "Code.exe", "attributes": {"pid": "13644"}, "children": []}, {"name": "bash.exe", "attributes": {"pid": "13832"}, "children": [{"name": "bash.exe", "children": []}]}, {"name": "SecurityHealthSystray.exe", "attributes": {"pid": "13940"}, "children": []}, {"name": "com.docker.service", "attributes": {"pid": "13952"}, "children": []}, {"name": "SecurityHealthService.exe", "attributes": {"pid": "13976"}, "children": []}, {"name": "Greenshot.exe", "attributes": {"pid": "14064"}, "children": []}, {"name": "bash.exe", "attributes": {"pid": "14092"}, "children": []}, {"name": "chrome.exe", "attributes": {"pid": "14128"}, "children": []}, {"name": "OneDrive.exe", "attributes": {"pid": "14244"}, "children": []}, {"name": "chrome.exe", "attributes": {"pid": "14356"}, "children": []}, {"name": "Code.exe", "attributes": {"pid": "14676"}, "children": [{"name": "Code.exe", "children": []}, {"name": "Code.exe", "children": []}, {"name": "Code.exe", "children": []}, {"name": "Code.exe", "children": [{"name": "Code.exe", "children": []}]}, {"name": "Code.exe", "children": []}]}, {"name": "audiodg.exe", "attributes": {"pid": "14732"}, "children": []}, {"name": "RuntimeBroker.exe", "attributes": {"pid": "14736"}, "children": []}, {"name": "PaintStudio.View.exe", "attributes": {"pid": "15024"}, "children": []}, {"name": "CompPkgSrv.exe", "attributes": {"pid": "15032"}, "children": []}, {"name": "RuntimeBroker.exe", "attributes": {"pid": "15352"}, "children": []}, {"name": "cmd.exe", "attributes": {"pid": "15464"}, "children": [{"name": "node.exe", "children": [{"name": "node.exe", "children": []}]}]}, {"name": "chrome.exe", "attributes": {"pid": "15512"}, "children": [{"name": "chrome.exe", "children": []}, {"name": "chrome.exe", "children": []}, {"name": "chrome.exe", "children": []}, {"name": "chrome.exe", "children": []}, {"name": "chrome.exe", "children": []}, {"name": "chrome.exe", "children": []}, {"name": "chrome.exe", "children": []}, {"name": "chrome.exe", "children": []}, {"name": "chrome.exe", "children": []}, {"name": "chrome.exe", "children": []}, {"name": "chrome.exe", "children": []}, {"name": "chrome.exe", "children": []}, {"name": "chrome.exe", "children": []}, {"name": "chrome.exe", "children": []}, {"name": "chrome.exe", "children": []}, {"name": "chrome.exe", "children": []}, {"name": "chrome.exe", "children": []}, {"name": "chrome.exe", "children": []}, {"name": "chrome.exe", "children": []}, {"name": "chrome.exe", "children": []}, {"name": "chrome.exe", "children": []}]}, {"name": "svchost.exe", "attributes": {"pid": "15528"}, "children": []}, {"name": "Code.exe", "attributes": {"pid": "15560"}, "children": []}, {"name": "Microsoft.Photos.exe", "attributes": {"pid": "15564"}, "children": []}, {"name": "svchost.exe", "attributes": {"pid": "15620"}, "children": []}, {"name": "client.exe", "attributes": {"pid": "15660"}, "children": []}, {"name": "svchost.exe", "attributes": {"pid": "15664"}, "children": []}, {"name": "winpty-agent.exe", "attributes": {"pid": "15756"}, "children": [{"name": "cmd.exe", "children": []}, {"name": "conhost.exe", "children": []}]}, {"name": "Postman.exe", "attributes": {"pid": "15824"}, "children": []}, {"name": "chrome.exe", "attributes": {"pid": "15868"}, "children": []}, {"name": "python.exe", "attributes": {"pid": "16124"}, "children": []}, {"name": "Code.exe", "attributes": {"pid": "16288"}, "children": [{"name": "conhost.exe", "children": []}, {"name": "bash.exe", "children": [{"name": "bash.exe", "children": []}]}, {"name": "bash.exe", "children": [{"name": "bash.exe", "children": []}]}, {"name": "Code.exe", "children": [{"name": "Code.exe", "children": []}, {"name": "Code.exe", "children": []}, {"name": "Code.exe", "children": []}, {"name": "Code.exe", "children": [{"name": "Code.exe", "children": []}]}, {"name": "Code.exe", "children": []}]}, {"name": "CodeHelper.exe", "children": [{"name": "conhost.exe", "children": []}]}, {"name": "conhost.exe", "children": []}]}, {"name": "MicrosoftEdge.exe", "attributes": {"pid": "16476"}, "children": []}, {"name": "svchost.exe", "attributes": {"pid": "16760"}, "children": []}, {"name": "Code.exe", "attributes": {"pid": "16792"}, "children": []}, {"name": "svchost.exe", "attributes": {"pid": "16888"}, "children": []}, {"name": "bash.exe", "attributes": {"pid": "16984"}, "children": [{"name": "python.exe", "children": []}]}, {"name": "conhost.exe", "attributes": {"pid": "17136"}, "children": []}, {"name": "git-bash.exe", "attributes": {"pid": "17160"}, "children": [{"name": "mintty.exe", "children": []}]}, {"name": "RuntimeBroker.exe", "attributes": {"pid": "17212"}, "children": []}, {"name": "Code.exe", "attributes": {"pid": "17272"}, "children": [{"name": "Code.exe", "children": []}]}, {"name": "MicrosoftEdgeCP.exe", "attributes": {"pid": "17344"}, "children": []}, {"name": "chrome.exe", "attributes": {"pid": "17360"}, "children": []}, {"name": "CodeHelper.exe", "attributes": {"pid": "17376"}, "children": [{"name": "conhost.exe", "children": []}]}, {"name": "conhost.exe", "attributes": {"pid": "17384"}, "children": []}, {"name": "client.exe", "attributes": {"pid": "17792"}, "children": [{"name": "client.exe", "children": []}]}, {"name": "python.exe", "attributes": {"pid": "17804"}, "children": [{"name": "python.exe", "children": []}]}, {"name": "Postman.exe", "attributes": {"pid": "17956"}, "children": []}, {"name": "Lenovo.Modern.ImController.PluginHost.Device.exe", "attributes": {"pid": "18024"}, "children": []}, {"name": "node.exe", "attributes": {"pid": "18104"}, "children": [{"name": "node.exe", "children": []}]}, {"name": "chrome.exe", "attributes": {"pid": "18192"}, "children": []}, {"name": "chrome.exe", "attributes": {"pid": "18252"}, "children": []}, {"name": "Postman.exe", "attributes": {"pid": "18260"}, "children": []}, {"name": "chrome.exe", "attributes": {"pid": "18352"}, "children": []}, {"name": "chrome.exe", "attributes": {"pid": "18396"}, "children": []}, {"name": "chrome.exe", "attributes": {"pid": "18440"}, "children": []}, {"name": "sh.exe", "attributes": {"pid": "18444"}, "children": [{"name": "sh.exe", "children": [{"name": "node.exe", "children": [{"name": "cmd.exe", "children": [{"name": "node.exe", "children": [{"name": "node.exe", "children": []}]}]}]}]}]}, {"name": "WmiPrvSE.exe", "attributes": {"pid": "18452"}, "children": []}, {"name": "chrome.exe", "attributes": {"pid": "18584"}, "children": []}, {"name": "svchost.exe", "attributes": {"pid": "18632"}, "children": []}, {"name": "node.exe", "attributes": {"pid": "18668"}, "children": []}, {"name": "Postman.exe", "attributes": {"pid": "19012"}, "children": [{"name": "Postman.exe", "children": []}, {"name": "Postman.exe", "children": []}, {"name": "Postman.exe", "children": []}, {"name": "Postman.exe", "children": []}, {"name": "Postman.exe", "children": []}]}, {"name": "svchost.exe", "attributes": {"pid": "19112"}, "children": []}, {"name": "chrome.exe", "attributes": {"pid": "19120"}, "children": []}, {"name": "chrome.exe", "attributes": {"pid": "19172"}, "children": []}, {"name": "Code.exe", "attributes": {"pid": "19192"}, "children": []}, {"name": "slack.exe", "attributes": {"pid": "19236"}, "children": []}, {"name": "client.exe", "attributes": {"pid": "19280"}, "children": []}, {"name": "postgres.exe", "attributes": {"pid": "19412"}, "children": []}, {"name": "runnerw64.exe", "attributes": {"pid": "19536"}, "children": [{"name": "conhost.exe", "children": []}, {"name": "python.exe", "children": [{"name": "python.exe", "children": []}]}]}, {"name": "conhost.exe", "attributes": {"pid": "19724"}, "children": []}, {"name": "unknown father", "attributes": {"pid": "732"}, "children": [{"name": "wininit.exe", "children": [{"name": "LsaIso.exe", "children": []}, {"name": "lsass.exe", "children": []}, {"name": "services.exe", "children": [{"name": "svchost.exe", "children": []}, {"name": "svchost.exe", "children": []}, {"name": "svchost.exe", "children": [{"name": "dllhost.exe", "children": []}, {"name": "SettingSyncHost.exe", "children": []}, {"name": "SystemSettings.exe", "children": []}, {"name": "WmiPrvSE.exe", "children": []}, {"name": "smartscreen.exe", "children": []}, {"name": "Calculator.exe", "children": []}, {"name": "browser_broker.exe", "children": []}, {"name": "unsecapp.exe", "children": []}, {"name": "RuntimeBroker.exe", "children": [{"name": "MicrosoftEdgeSH.exe", "children": []}]}, {"name": "YourPhone.exe", "children": []}, {"name": "RuntimeBroker.exe", "children": []}, {"name": "ApplicationFrameHost.exe", "children": []}, {"name": "StartMenuExperienceHost.exe", "children": []}, {"name": "WindowsInternal.ComposableShell.Experiences.TextInput.InputApp.exe", "children": []}, {"name": "RuntimeBroker.exe", "children": []}, {"name": "YourPhoneServer.exe", "children": []}, {"name": "SearchUI.exe", "children": []}, {"name": "RuntimeBroker.exe", "children": []}, {"name": "ShellExperienceHost.exe", "children": []}, {"name": "SkypeApp.exe", "children": []}, {"name": "SkypeBackgroundHost.exe", "children": []}, {"name": "LockApp.exe", "children": []}, {"name": "RuntimeBroker.exe", "children": []}, {"name": "RuntimeBroker.exe", "children": []}, {"name": "igfxext.exe", "children": []}, {"name": "RuntimeBroker.exe", "children": [{"name": "SkypeBridge.exe", "children": []}]}, {"name": "SecurityHealthHost.exe", "children": []}, {"name": "RuntimeBroker.exe", "children": []}, {"name": "CompPkgSrv.exe", "children": []}, {"name": "RuntimeBroker.exe", "children": []}, {"name": "Microsoft.Photos.exe", "children": []}, {"name": "MicrosoftEdge.exe", "children": []}, {"name": "RuntimeBroker.exe", "children": []}, {"name": "MicrosoftEdgeCP.exe", "children": []}, {"name": "WmiPrvSE.exe", "children": []}]}, {"name": "WUDFHost.exe", "children": []}, {"name": "svchost.exe", "children": []}, {"name": "svchost.exe", "children": []}, {"name": "svchost.exe", "children": []}, {"name": "WUDFHost.exe", "children": []}, {"name": "WUDFHost.exe", "children": []}, {"name": "WUDFHost.exe", "children": []}, {"name": "svchost.exe", "children": []}, {"name": "svchost.exe", "children": []}, {"name": "svchost.exe", "children": []}, {"name": "svchost.exe", "children": []}, {"name": "svchost.exe", "children": []}, {"name": "svchost.exe", "children": []}, {"name": "svchost.exe", "children": []}, {"name": "svchost.exe", "children": []}, {"name": "svchost.exe", "children": []}, {"name": "svchost.exe", "children": []}, {"name": "svchost.exe", "children": []}, {"name": "svchost.exe", "children": []}, {"name": "svchost.exe", "children": []}, {"name": "svchost.exe", "children": []}, {"name": "svchost.exe", "children": []}, {"name": "svchost.exe", "children": []}, {"name": "svchost.exe", "children": []}, {"name": "svchost.exe", "children": [{"name": "dasHost.exe", "children": []}]}, {"name": "igfxCUIService.exe", "children": [{"name": "igfxEM.exe", "children": []}]}, {"name": "svchost.exe", "children": []}, {"name": "LITSSvc.exe", "children": []}, {"name": "ibmpmsvc.exe", "children": []}, {"name": "svchost.exe", "children": []}, {"name": "svchost.exe", "children": [{"name": "sihost.exe", "children": [{"name": "PaintStudio.View.exe", "children": []}]}]}, {"name": "svchost.exe", "children": []}, {"name": "svchost.exe", "children": []}, {"name": "svchost.exe", "children": []}, {"name": "svchost.exe", "children": []}, {"name": "svchost.exe", "children": [{"name": "taskhostw.exe", "children": []}, {"name": "PowerMgr.exe", "children": []}, {"name": "RtkAudUService64.exe", "children": []}]}, {"name": "svchost.exe", "children": []}, {"name": "spoolsv.exe", "children": []}, {"name": "svchost.exe", "children": []}, {"name": "svchost.exe", "children": []}, {"name": "svchost.exe", "children": []}, {"name": "svchost.exe", "children": []}, {"name": "svchost.exe", "children": []}, {"name": "svchost.exe", "children": []}, {"name": "svchost.exe", "children": [{"name": "audiodg.exe", "children": []}]}, {"name": "svchost.exe", "children": []}, {"name": "svchost.exe", "children": []}, {"name": "svchost.exe", "children": []}, {"name": "svchost.exe", "children": [{"name": "wlanext.exe", "children": [{"name": "conhost.exe", "children": []}]}]}, {"name": "svchost.exe", "children": []}, {"name": "SgrmBroker.exe", "children": []}, {"name": "svchost.exe", "children": []}, {"name": "svchost.exe", "children": []}, {"name": "svchost.exe", "children": []}, {"name": "svchost.exe", "children": []}, {"name": "svchost.exe", "children": []}, {"name": "svchost.exe", "children": []}, {"name": "svchost.exe", "children": []}, {"name": "svchost.exe", "children": []}, {"name": "IntelCpHDCPSvc.exe", "children": []}, {"name": "svchost.exe", "children": []}, {"name": "DAX3API.exe", "children": [{"name": "DAX3API.exe", "children": []}]}, {"name": "svchost.exe", "children": []}, {"name": "Lenovo.Modern.ImController.exe", "children": [{"name": "Lenovo.Modern.ImController.PluginHost.SettingsApp.exe", "children": []}, {"name": "Lenovo.Modern.ImController.PluginHost.CompanionApp.exe", "children": []}, {"name": "Lenovo.Modern.ImController.PluginHost.Device.exe", "children": []}]}, {"name": "esif_uf.exe", "children": []}, {"name": "svchost.exe", "children": []}, {"name": "ApsInsSvc.exe", "children": []}, {"name": "EvtEng.exe", "children": []}, {"name": "FMService64.exe", "children": []}, {"name": "svchost.exe", "children": []}, {"name": "ThunderboltService.exe", "children": []}, {"name": "svchost.exe", "children": []}, {"name": "svchost.exe", "children": []}, {"name": "LMS.exe", "children": []}, {"name": "pg_ctl.exe", "children": [{"name": "postgres.exe", "children": [{"name": "postgres.exe", "children": []}, {"name": "postgres.exe", "children": []}, {"name": "postgres.exe", "children": []}, {"name": "conhost.exe", "children": []}, {"name": "postgres.exe", "children": []}, {"name": "postgres.exe", "children": []}, {"name": "postgres.exe", "children": []}, {"name": "postgres.exe", "children": []}, {"name": "postgres.exe", "children": []}, {"name": "postgres.exe", "children": []}, {"name": "postgres.exe", "children": []}, {"name": "postgres.exe", "children": []}, {"name": "postgres.exe", "children": []}, {"name": "postgres.exe", "children": []}, {"name": "postgres.exe", "children": []}]}]}, {"name": "svchost.exe", "children": []}, {"name": "WirelessKB850NotificationService.exe", "children": []}, {"name": "Updater.exe", "children": []}, {"name": "SynTPEnhService.exe", "children": [{"name": "SynTPEnh.exe", "children": []}]}, {"name": "RtkAudUService64.exe", "children": [{"name": "RtkAudUService64.exe", "children": []}]}, {"name": "SocketHeciServer.exe", "children": []}, {"name": "MsMpEng.exe", "children": []}, {"name": "ZeroConfigService.exe", "children": []}, {"name": "EasyResume.exe", "children": []}, {"name": "mongod.exe", "children": []}, {"name": "svchost.exe", "children": []}, {"name": "svchost.exe", "children": []}, {"name": "svchost.exe", "children": []}, {"name": "svchost.exe", "children": []}, {"name": "tphkload.exe", "children": [{"name": "shtctky.exe", "children": []}, {"name": "tposd.exe", "children": []}]}, {"name": "vmms.exe", "children": []}, {"name": "LenovoVantageService.exe", "children": []}, {"name": "IntelCpHeciSvc.exe", "children": []}, {"name": "DolbyDAX2API.exe", "children": []}, {"name": "jhi_service.exe", "children": []}, {"name": "vmcompute.exe", "children": []}, {"name": "svchost.exe", "children": []}, {"name": "svchost.exe", "children": []}, {"name": "svchost.exe", "children": []}, {"name": "svchost.exe", "children": []}, {"name": "NisSrv.exe", "children": []}, {"name": "tbtsvc.exe", "children": []}, {"name": "svchost.exe", "children": []}, {"name": "svchost.exe", "children": []}, {"name": "svchost.exe", "children": []}, {"name": "svchost.exe", "children": []}, {"name": "svchost.exe", "children": []}, {"name": "svchost.exe", "children": []}, {"name": "svchost.exe", "children": [{"name": "ctfmon.exe", "children": []}]}, {"name": "svchost.exe", "children": []}, {"name": "svchost.exe", "children": []}, {"name": "svchost.exe", "children": []}, {"name": "svchost.exe", "children": []}, {"name": "svchost.exe", "children": []}, {"name": "svchost.exe", "children": []}, {"name": "svchost.exe", "children": []}, {"name": "SearchIndexer.exe", "children": [{"name": "SearchFilterHost.exe", "children": []}, {"name": "SearchProtocolHost.exe", "children": []}]}, {"name": "svchost.exe", "children": []}, {"name": "svchost.exe", "children": []}, {"name": "aesm_service.exe", "children": []}, {"name": "com.docker.service", "children": []}, {"name": "SecurityHealthService.exe", "children": []}, {"name": "svchost.exe", "children": []}, {"name": "svchost.exe", "children": []}, {"name": "svchost.exe", "children": []}, {"name": "svchost.exe", "children": []}, {"name": "svchost.exe", "children": []}, {"name": "svchost.exe", "children": []}, {"name": "svchost.exe", "children": []}]}, {"name": "fontdrvhost.exe", "children": []}]}]}, {"name": "unknown father", "attributes": {"pid": "936"}, "children": [{"name": "winlogon.exe", "children": [{"name": "fontdrvhost.exe", "children": []}, {"name": "dwm.exe", "children": []}]}]}, {"name": "unknown father", "attributes": {"pid": "7872"}, "children": []}, {"name": "unknown father", "attributes": {"pid": "15816"}, "children": []}, {"name": "unknown father", "attributes": {"pid": "9956"}, "children": []}, {"name": "unknown father", "attributes": {"pid": "8096"}, "children": []}, {"name": "unknown father", "attributes": {"pid": "8932"}, "children": [{"name": "GoogleCrashHandler64.exe", "children": []}]}, {"name": "unknown father", "attributes": {"pid": "9420"}, "children": []}, {"name": "unknown father", "attributes": {"pid": "13848"}, "children": []}, {"name": "unknown father", "attributes": {"pid": "11032"}, "children": []}, {"name": "unknown father", "attributes": {"pid": "17420"}, "children": []}, {"name": "unknown father", "attributes": {"pid": "14352"}, "children": []}, {"name": "unknown father", "attributes": {"pid": "9136"}, "children": []}, {"name": "unknown father", "attributes": {"pid": "18436"}, "children": []}]}